tldw/__init__.py
tldw/tldw.py
tldw-1.0.4.dist-info/licenses/LICENSE
tldw-1.0.4.dist-info/METADATA
tldw-1.0.4.dist-info/WHEEL
tldw-1.0.4.dist-info/top_level.txt
tldw-1.0.4.dist-info/RECORD
