Metadata-Version: 2.4
Name: tldw
Version: 1.0.4
Summary: A Python package to summarize YouTube videos using the OpenAI API.
Author-email: David Zirinsky <dzirinsky@gmail.com>
Project-URL: Homepage, https://github.com/DavidZirinsky/tl-dw
Project-URL: Bug Tracker, https://github.com/DavidZirinsky/tl-dw/issues
Project-URL: Source, https://github.com/DavidZirinsky/tl-dw
Classifier: Programming Language :: Python :: 3
Classifier: License :: OSI Approved :: MIT License
Classifier: Operating System :: OS Independent
Requires-Python: >=3.8
License-File: LICENSE
Requires-Dist: requests>=2.31.0
Requires-Dist: youtube-transcript-api>=1.0.3
Requires-Dist: pyfiglet>=0.8.post1
Requires-Dist: termcolor>=2.4.0
Dynamic: license-file
